ruia_ua/__init__.py
ruia_ua/user_agents.txt
ruia_ua-0.0.2.dist-info/LICENSE
ruia_ua-0.0.2.dist-info/METADATA
ruia_ua-0.0.2.dist-info/WHEEL
ruia_ua-0.0.2.dist-info/top_level.txt
ruia_ua-0.0.2.dist-info/RECORD
