Metadata-Version: 2.1
Name: ruia-ua
Version: 0.0.2
Summary: ruia_ua - simple user-agent middleware for Ruia.
Home-page: https://github.com/python-ruia/ruia-ua
Author: Howie Hu
Author-email: xiaozizayang@gmail.com
License: MIT
Project-URL: Documentation, https://github.com/python-ruia/ruia-ua
Project-URL: Source, https://github.com/python-ruia/ruia-ua
Platform: UNKNOWN
Classifier: Intended Audience :: Developers
Classifier: License :: OSI Approved :: MIT License
Classifier: Programming Language :: Python :: 3.6
Classifier: Programming Language :: Python :: 3.7
Classifier: Topic :: Software Development :: Libraries :: Python Modules
Requires-Dist: aiofiles
Requires-Dist: ruia (>=0.5.1)
